HISTORY.rst
LICENSE
MANIFEST.in
README.md
README.rst
__about__.py
flask_pretty.py
setup.py
Flask_Pretty.egg-info/PKG-INFO
Flask_Pretty.egg-info/SOURCES.txt
Flask_Pretty.egg-info/dependency_links.txt
Flask_Pretty.egg-info/not-zip-safe
Flask_Pretty.egg-info/requires.txt
Flask_Pretty.egg-info/top_level.txt
docs/Makefile
docs/conf.py
docs/index.rst
docs/make.bat
flask_pretty.egg-info/PKG-INFO
flask_pretty.egg-info/SOURCES.txt
flask_pretty.egg-info/dependency_links.txt
flask_pretty.egg-info/not-zip-safe
flask_pretty.egg-info/requires.txt
flask_pretty.egg-info/top_level.txt
tests/test_pretty.py
tests/templates/pretty.html
tests/templates/ugly.html